scopespace.py
scopespace-0.0.1.dist-info/METADATA
scopespace-0.0.1.dist-info/WHEEL
scopespace-0.0.1.dist-info/licenses/LICENSE
scopespace-0.0.1.dist-info/RECORD
